<?xml version="1.0" encoding="UTF-8"?>
<node>
<version>6</version>
<dict>
  <key>title</key><string>vue</string>
  <key>nodeid</key><string>e0ff064b-a68f-4d73-bc39-dab453373900</string>
  <key>modified_time</key><integer>1583400877</integer>
  <key>version</key><integer>6</integer>
  <key>content_type</key><string>text/xhtml+xml</string>
  <key>created_time</key><integer>1583400865</integer>
  <key>info_sort_dir</key><integer>1</integer>
  <key>order</key><integer>1</integer>
  <key>info_sort</key><string>order</string>
</dict>
</node>
